mlcook/__init__.py
mlcook/experiment/__init__.py
mlcook/experiment/classification_experiment.py
mlcook/experiment/drift_analyzer.py
mlcook/experiment/evaluator.py
mlcook/experiment/explainer.py
mlcook/experiment/i_experiment.py
mlcook/experiment/old_code.py
mlcook/experiment/post_processor.py
mlcook/experiment/predictor.py
mlcook/experiment/preprocessor.py
mlcook/experiment/stat_utils.py
mlcook/experiment/trainer.py
mlcook/experiment/utils.py
mlcook/model/__init__.py
mlcook/model/classifier.py
mlcook/model/nlp_classifier.py
mlcook/plot/__init__.py
mlcook/plot/plot_classification.py
mlcook/plot/plot_regression.py
mlcook-0.0.1.dist-info/LICENSE.txt
mlcook-0.0.1.dist-info/METADATA
mlcook-0.0.1.dist-info/WHEEL
mlcook-0.0.1.dist-info/top_level.txt
mlcook-0.0.1.dist-info/RECORD
