Metadata-Version: 2.1
Name: mlcook
Version: 0.0.1
Summary: A personal ml toolbox
Home-page: UNKNOWN
Author: Yohann Le Faou
Author-email: lefaou.yohann@gmail.com
License: MIT
Platform: UNKNOWN
Classifier: Intended Audience :: Science/Research
Classifier: Intended Audience :: Developers
Classifier: Topic :: Software Development
Classifier: Topic :: Scientific/Engineering
Classifier: Programming Language :: Python :: 3
Classifier: License :: OSI Approved :: MIT License
Classifier: Operating System :: OS Independent
Requires-Python: >=3.7
License-File: LICENSE.txt
